crlite_query/__init__.py
crlite_query/query_cli.py
crlite_query/test_query_cli.py
moz_crlite_query-0.5.0.dist-info/LICENSE
moz_crlite_query-0.5.0.dist-info/METADATA
moz_crlite_query-0.5.0.dist-info/WHEEL
moz_crlite_query-0.5.0.dist-info/entry_points.txt
moz_crlite_query-0.5.0.dist-info/top_level.txt
moz_crlite_query-0.5.0.dist-info/RECORD
