Metadata-Version: 2.1
Name: moz-crlite-query
Version: 0.5.0
Summary: Query CRLite for a certificate, or certificate information
Home-page: http://github.com/mozilla/moz_crlite_query
Author: J.C. Jones
Author-email: jc@mozilla.com
License: Mozilla Public License 2.0 (MPL 2.0)
Keywords: bloom filter cascade multi level mlbf crlite
Platform: UNKNOWN
Classifier: Development Status :: 4 - Beta
Classifier: License :: OSI Approved :: Mozilla Public License 2.0 (MPL 2.0)
Classifier: Programming Language :: Python :: 3
Requires-Python: >=3.7
License-File: LICENSE
Requires-Dist: deprecated
Requires-Dist: filtercascade
Requires-Dist: glog
Requires-Dist: moz-crlite-lib
Requires-Dist: progressbar2
Requires-Dist: pyasn1-modules
Requires-Dist: requests
